featuretools/__init__.py
featuretools/__main__.py
featuretools/config_init.py
featuretools/exceptions.py
featuretools/version.py
featuretools/computational_backends/__init__.py
featuretools/computational_backends/api.py
featuretools/computational_backends/calculate_feature_matrix.py
featuretools/computational_backends/feature_set.py
featuretools/computational_backends/feature_set_calculator.py
featuretools/computational_backends/utils.py
featuretools/demo/__init__.py
featuretools/demo/api.py
featuretools/demo/flight.py
featuretools/demo/mock_customer.py
featuretools/demo/retail.py
featuretools/demo/weather.py
featuretools/entityset/__init__.py
featuretools/entityset/api.py
featuretools/entityset/deserialize.py
featuretools/entityset/entityset.py
featuretools/entityset/relationship.py
featuretools/entityset/serialize.py
featuretools/entityset/timedelta.py
featuretools/feature_base/__init__.py
featuretools/feature_base/api.py
featuretools/feature_base/cache.py
featuretools/feature_base/feature_base.py
featuretools/feature_base/feature_descriptions.py
featuretools/feature_base/feature_visualizer.py
featuretools/feature_base/features_deserializer.py
featuretools/feature_base/features_serializer.py
featuretools/feature_base/utils.py
featuretools/feature_discovery/FeatureCollection.py
featuretools/feature_discovery/LiteFeature.py
featuretools/feature_discovery/__init__.py
featuretools/feature_discovery/convertors.py
featuretools/feature_discovery/feature_discovery.py
featuretools/feature_discovery/type_defs.py
featuretools/feature_discovery/utils.py
featuretools/primitives/__init__.py
featuretools/primitives/options_utils.py
featuretools/primitives/utils.py
featuretools/primitives/base/__init__.py
featuretools/primitives/base/aggregation_primitive_base.py
featuretools/primitives/base/primitive_base.py
featuretools/primitives/base/transform_primitive_base.py
featuretools/primitives/data/featuretools_unit_test_example.csv
featuretools-1.31.0.dist-info/LICENSE
featuretools-1.31.0.dist-info/METADATA
featuretools-1.31.0.dist-info/WHEEL
featuretools-1.31.0.dist-info/free_email_provider_domains_license
featuretools-1.31.0.dist-info/top_level.txt
featuretools-1.31.0.dist-info/RECORD
