Metadata-Version: 2.1
Name: featuretools
Version: 1.31.0
Summary: a framework for automated feature engineering
Author-email: "Alteryx, Inc." <open_source_support@alteryx.com>
Maintainer-email: "Alteryx, Inc." <open_source_support@alteryx.com>
License: BSD 3-clause
Project-URL: Documentation, https://featuretools.alteryx.com
Project-URL: Source Code, https://github.com/alteryx/featuretools/
Project-URL: Changes, https://featuretools.alteryx.com/en/latest/release_notes.html
Project-URL: Issue Tracker, https://github.com/alteryx/featuretools/issues
Project-URL: Twitter, https://twitter.com/alteryxoss
Project-URL: Chat, https://join.slack.com/t/alteryx-oss/shared_invite/zt-182tyvuxv-NzIn6eiCEf8TBziuKp0bNA
Keywords: feature engineering,data science,machine learning
Classifier: Development Status :: 5 - Production/Stable
Classifier: Intended Audience :: Science/Research
Classifier: Intended Audience :: Developers
Classifier: Topic :: Software Development
Classifier: Topic :: Scientific/Engineering
Classifier: Programming Language :: Python
Classifier: Programming Language :: Python :: 3
Classifier: Programming Language :: Python :: 3.9
Classifier: Programming Language :: Python :: 3.10
Classifier: Programming Language :: Python :: 3.11
Classifier: Programming Language :: Python :: 3.12
Classifier: Operating System :: Microsoft :: Windows
Classifier: Operating System :: POSIX
Classifier: Operating System :: Unix
Classifier: Operating System :: MacOS
Requires-Python: <4,>=3.9
License-File: LICENSE
License-File: featuretools/primitives/data/free_email_provider_domains_license
Requires-Dist: cloudpickle>=1.5.0
Requires-Dist: holidays>=0.17
Requires-Dist: numpy>=1.25.0
Requires-Dist: packaging>=20.0
Requires-Dist: pandas>=2.0.0
Requires-Dist: psutil>=5.7.0
Requires-Dist: scipy>=1.10.0
Requires-Dist: tqdm>=4.66.3
Requires-Dist: woodwork>=0.28.0
Provides-Extra: test
Requires-Dist: boto3>=1.34.32; extra == "test"
Requires-Dist: composeml>=0.8.0; extra == "test"
Requires-Dist: graphviz>=0.8.4; extra == "test"
Requires-Dist: moto[all]>=5.0.0; extra == "test"
Requires-Dist: pip>=23.3.0; extra == "test"
Requires-Dist: pyarrow>=14.0.1; extra == "test"
Requires-Dist: pympler>=0.8; extra == "test"
Requires-Dist: pytest>=7.1.2; extra == "test"
Requires-Dist: pytest-cov>=3.0.0; extra == "test"
Requires-Dist: pytest-xdist>=2.5.0; extra == "test"
Requires-Dist: smart-open>=5.0.0; extra == "test"
Requires-Dist: urllib3>=1.26.18; extra == "test"
Requires-Dist: pytest-timeout>=2.1.0; extra == "test"
Provides-Extra: dask
Requires-Dist: dask[dataframe]>=2023.2.0; extra == "dask"
Requires-Dist: distributed>=2023.2.0; extra == "dask"
Provides-Extra: tsfresh
Requires-Dist: featuretools-tsfresh-primitives>=1.0.0; extra == "tsfresh"
Provides-Extra: autonormalize
Requires-Dist: autonormalize>=2.0.1; extra == "autonormalize"
Provides-Extra: sql
Requires-Dist: featuretools_sql>=0.0.1; extra == "sql"
Requires-Dist: psycopg2-binary>=2.9.3; extra == "sql"
Provides-Extra: sklearn
Requires-Dist: featuretools-sklearn-transformer>=1.0.0; extra == "sklearn"
Provides-Extra: premium
Requires-Dist: premium-primitives>=0.0.3; extra == "premium"
Provides-Extra: nlp
Requires-Dist: nlp-primitives>=2.12.0; extra == "nlp"
Provides-Extra: docs
Requires-Dist: ipython==8.4.0; extra == "docs"
Requires-Dist: jupyter==1.0.0; extra == "docs"
Requires-Dist: jupyter-client>=8.0.2; extra == "docs"
Requires-Dist: matplotlib==3.7.2; extra == "docs"
Requires-Dist: Sphinx==5.1.1; extra == "docs"
Requires-Dist: nbsphinx==0.8.9; extra == "docs"
Requires-Dist: nbconvert==6.5.0; extra == "docs"
Requires-Dist: pydata-sphinx-theme==0.9.0; extra == "docs"
Requires-Dist: sphinx-inline-tabs==2022.1.2b11; extra == "docs"
Requires-Dist: sphinx-copybutton==0.5.0; extra == "docs"
Requires-Dist: myst-parser==0.18.0; extra == "docs"
Requires-Dist: autonormalize>=2.0.1; extra == "docs"
Requires-Dist: click>=7.0.0; extra == "docs"
Requires-Dist: featuretools[dask,test]; extra == "docs"
Provides-Extra: dev
Requires-Dist: ruff>=0.1.6; extra == "dev"
Requires-Dist: black[jupyter]>=23.1.0; extra == "dev"
Requires-Dist: pre-commit>=2.20.0; extra == "dev"
Requires-Dist: featuretools[dask,docs,test]; extra == "dev"
Provides-Extra: complete
Requires-Dist: featuretools[dask,nlp,premium]; extra == "complete"
